{
    "configurations": [
        {
            "name": "Linux",
            "includePath": [
                "${workspaceFolder}/**",
                "/usr/include",
                "/usr/local/include",
                "/usr/include/x86_64-linux-gnu",
                "/usr/include/cjson"
            ],
            "defines": [],
            "compilerPath": "/usr/bin/gcc",
            "cStandard": "c11",
            "cppStandard": "c++17",
            "intelliSenseMode": "gcc-x64",
            "browse": {
                "path": [
                    "/usr/include",
                    "/usr/local/include",
                    "/usr/include/cjson"
                ],
                "limitSymbolsToIncludedHeaders": true
            }
        }
    ],
    "version": 4
}
